mozichem_mcp/__init__.py
mozichem_mcp/mcp/__init__.py
mozichem_mcp/mcp/eos_models.py
mozichem_mcp/mcp/flash_calculation.py
mozichem_mcp-0.1.0.dist-info/METADATA
mozichem_mcp-0.1.0.dist-info/WHEEL
mozichem_mcp-0.1.0.dist-info/entry_points.txt
mozichem_mcp-0.1.0.dist-info/licenses/LICENSE
mozichem_mcp-0.1.0.dist-info/RECORD
