Metadata-Version: 2.4
Name: mozichem-mcp
Version: 0.1.0
Summary: MoziChem MCP tools built on top of the MoziChem framework
Project-URL: Homepage, https://github.com/sinagilassi/mozichem-mcp
Author-email: Sina Gilassi <sina.gilassi@gmail.com>
License-Expression: MIT
License-File: LICENSE
Requires-Python: >=3.13
Requires-Dist: mozichem-hub>=0.1.2
Provides-Extra: dev
Requires-Dist: black; extra == 'dev'
Requires-Dist: pytest; extra == 'dev'
Requires-Dist: ruff; extra == 'dev'
